MANIFEST.in
README.md
setup.cfg
setup.py
moziris/__init__.py
moziris.egg-info/PKG-INFO
moziris.egg-info/SOURCES.txt
moziris.egg-info/dependency_links.txt
moziris.egg-info/entry_points.txt
moziris.egg-info/not-zip-safe
moziris.egg-info/requires.txt
moziris.egg-info/top_level.txt
moziris/api/__init__.py
moziris/api/enums.py
moziris/api/errors.py
moziris/api/location.py
moziris/api/os_helpers.py
moziris/api/rectangle.py
moziris/api/settings.py
moziris/api/finder/__init__.py
moziris/api/finder/finder.py
moziris/api/finder/image_search.py
moziris/api/finder/pattern.py
moziris/api/finder/text_search.py
moziris/api/highlight/__init__.py
moziris/api/highlight/highlight_circle.py
moziris/api/highlight/highlight_rectangle.py
moziris/api/highlight/screen_highlight.py
moziris/api/keyboard/__init__.py
moziris/api/keyboard/key.py
moziris/api/keyboard/keyboard.py
moziris/api/keyboard/keyboard_api.py
moziris/api/keyboard/keyboard_util.py
moziris/api/mouse/__init__.py
moziris/api/mouse/mouse.py
moziris/api/mouse/mouse_controller.py
moziris/api/mouse/xmouse.py
moziris/api/save_debug_image/__init__.py
moziris/api/save_debug_image/save_image.py
moziris/api/screen/__init__.py
moziris/api/screen/display.py
moziris/api/screen/region.py
moziris/api/screen/region_utils.py
moziris/api/screen/screen.py
moziris/api/screen/screenshot_image.py
moziris/base/__init__.py
moziris/base/target.py
moziris/base/testcase.py
moziris/configuration/__init__.py
moziris/configuration/config_parser.py
moziris/control_center/__init__.py
moziris/control_center/commands.py
moziris/control_center/assets/.DS_Store
moziris/control_center/assets/asset-manifest.json
moziris/control_center/assets/favicon.ico
moziris/control_center/assets/index.html
moziris/control_center/assets/manifest.json
moziris/control_center/assets/service-worker.js
moziris/control_center/assets/images/firefox.png
moziris/control_center/assets/images/notepad.png
moziris/control_center/assets/static/.DS_Store
moziris/control_center/assets/static/css/2.3c6b4139.chunk.css
moziris/control_center/assets/static/css/2.3c6b4139.chunk.css.map
moziris/control_center/assets/static/css/main.c73dc7db.chunk.css
