Metadata-Version: 2.1
Name: moziris
Version: 0.8.2
Summary: Automation tool for visual testing
Home-page: https://github.com/mozilla/iris
Author: Mozilla
Author-email: mwobensmith@mozilla.com
License: MPL2
Download-URL: https://github.com/mozilla/iris/latest.tar.gz
Keywords: automation,testing
Platform: UNKNOWN
Classifier: Environment :: Console
Classifier: Development Status :: 4 - Beta
Classifier: Intended Audience :: Developers
Classifier: License :: OSI Approved :: Mozilla Public License 2.0 (MPL 2.0)
Classifier: Natural Language :: English
Classifier: Operating System :: MacOS :: MacOS X
Classifier: Operating System :: Microsoft :: Windows :: Windows 10
Classifier: Operating System :: Microsoft :: Windows :: Windows 7
Classifier: Operating System :: Microsoft :: Windows :: Windows 8
Classifier: Operating System :: Microsoft :: Windows :: Windows 8.1
Classifier: Operating System :: POSIX :: Linux
Classifier: Programming Language :: Python :: 3.7
Classifier: Topic :: Software Development :: Quality Assurance
Classifier: Topic :: Software Development :: Testing
Requires-Python: >=3.7.3
Provides-Extra: dev
